unified_ai/__init__.py
lifeaitools_sdk-0.0.1.dist-info/METADATA
lifeaitools_sdk-0.0.1.dist-info/WHEEL
lifeaitools_sdk-0.0.1.dist-info/licenses/LICENSE
lifeaitools_sdk-0.0.1.dist-info/RECORD
