Metadata-Version: 2.4
Name: lifeaitools-sdk
Version: 0.0.1
Summary: Unified AI SDK - Multi-provider AI abstraction layer with fallback support
Project-URL: Homepage, https://github.com/lifeaitools/lifeaitools-sdk
Author-email: LifeAiTools Dev Team <dev@lifeaitools.com>
License-Expression: Apache-2.0
License-File: LICENSE
Keywords: ai,elevenlabs,fallback,gemini,llm,openai,tts,unified
Classifier: Development Status :: 2 - Pre-Alpha
Classifier: Intended Audience :: Developers
Classifier: License :: OSI Approved :: Apache Software License
Classifier: Programming Language :: Python :: 3
Classifier: Programming Language :: Python :: 3.10
Classifier: Programming Language :: Python :: 3.11
Classifier: Programming Language :: Python :: 3.12
Requires-Python: >=3.10
